redis_throttled_queue/__init__.py
redis_throttled_queue/library.lua
redis_throttled_queue-1.0.0.dist-info/AUTHORS.rst
redis_throttled_queue-1.0.0.dist-info/LICENSE
redis_throttled_queue-1.0.0.dist-info/METADATA
redis_throttled_queue-1.0.0.dist-info/WHEEL
redis_throttled_queue-1.0.0.dist-info/top_level.txt
redis_throttled_queue-1.0.0.dist-info/RECORD
